Indium/Notifiy.py
Indium/TuiElements.py
Indium/__init__.py
Indium/configs.py
Indium/heading.py
Indium/loaders.py
indium_nd-0.2.2.dist-info/licenses/LICENSE
indium_nd-0.2.2.dist-info/METADATA
indium_nd-0.2.2.dist-info/WHEEL
indium_nd-0.2.2.dist-info/top_level.txt
indium_nd-0.2.2.dist-info/RECORD
