Metadata-Version: 2.4
Name: Indium-ND
Version: 0.2.2
Summary: Utility package with file operations and ASCII headings
Author: Sayon
Author-email: codewithsayon@gmail.com
Requires-Python: >=3.7
License-File: LICENSE
Requires-Dist: pyfiglet
Requires-Dist: colorama
Requires-Dist: pyautogui
Requires-Dist: yaspin
Requires-Dist: alive-progress
Requires-Dist: rich
Requires-Dist: InquirerPy
Requires-Dist: tabulate
Requires-Dist: keyboard
Dynamic: author
Dynamic: author-email
Dynamic: description-content-type
Dynamic: license-file
Dynamic: requires-dist
Dynamic: requires-python
Dynamic: summary
